gd32graphing/__init__.py
gd32graphing/graphing.py
gd32graphing-0.0.3.dist-info/METADATA
gd32graphing-0.0.3.dist-info/WHEEL
gd32graphing-0.0.3.dist-info/top_level.txt
gd32graphing-0.0.3.dist-info/RECORD
